ToeflIbtGaofenZuowen/README.md
ToeflIbtGaofenZuowen/__init__.py
ToeflIbtGaofenZuowen/__main__.py
ToeflIbtGaofenZuowen/file.epub
ToeflIbtGaofenZuowen/index.html
ToeflIbtGaofenZuowen/css/__init__.py
ToeflIbtGaofenZuowen/css/annotations.css
ToeflIbtGaofenZuowen/css/main.css
ToeflIbtGaofenZuowen/css/normalize.css
ToeflIbtGaofenZuowen/css/popup.css
ToeflIbtGaofenZuowen/font/__init__.py
ToeflIbtGaofenZuowen/font/fontello.eot
ToeflIbtGaofenZuowen/font/fontello.svg
ToeflIbtGaofenZuowen/font/fontello.ttf
ToeflIbtGaofenZuowen/font/fontello.woff
ToeflIbtGaofenZuowen/img/__init__.py
ToeflIbtGaofenZuowen/img/annotator-glyph-sprite.png
ToeflIbtGaofenZuowen/img/annotator-icon-sprite.png
ToeflIbtGaofenZuowen/img/apple-touch-icon.png
ToeflIbtGaofenZuowen/img/cancelfullscreen.png
ToeflIbtGaofenZuowen/img/close.png
ToeflIbtGaofenZuowen/img/fullscreen.png
ToeflIbtGaofenZuowen/img/loader.gif
ToeflIbtGaofenZuowen/img/menu-icon.png
ToeflIbtGaofenZuowen/img/save.png
ToeflIbtGaofenZuowen/img/saved.png
ToeflIbtGaofenZuowen/img/settings-s.png
ToeflIbtGaofenZuowen/img/settings.png
ToeflIbtGaofenZuowen/img/star.png
ToeflIbtGaofenZuowen/js/__init__.py
ToeflIbtGaofenZuowen/js/epub.js
ToeflIbtGaofenZuowen/js/epub.min.js
ToeflIbtGaofenZuowen/js/epub.min.map
ToeflIbtGaofenZuowen/js/hooks.min.js
ToeflIbtGaofenZuowen/js/hooks.min.map
ToeflIbtGaofenZuowen/js/reader.js
ToeflIbtGaofenZuowen/js/reader.js.map
ToeflIbtGaofenZuowen/js/reader.min.js
ToeflIbtGaofenZuowen/js/reader.min.map
ToeflIbtGaofenZuowen/js/hooks/__init__.py
ToeflIbtGaofenZuowen/js/hooks/extensions/__init__.py
ToeflIbtGaofenZuowen/js/hooks/extensions/highlight.js
ToeflIbtGaofenZuowen/js/libs/__init__.py
ToeflIbtGaofenZuowen/js/libs/jquery.min.js
ToeflIbtGaofenZuowen/js/libs/localforage.min.js
ToeflIbtGaofenZuowen/js/libs/screenfull.js
ToeflIbtGaofenZuowen/js/libs/screenfull.min.js
ToeflIbtGaofenZuowen/js/libs/zip.min.js
ToeflIbtGaofenZuowen/js/plugins/__init__.py
ToeflIbtGaofenZuowen/js/plugins/hypothesis.js
toefl_ibt_gaofen_zuowen-2024.3.5.0.dist-info/METADATA
toefl_ibt_gaofen_zuowen-2024.3.5.0.dist-info/WHEEL
toefl_ibt_gaofen_zuowen-2024.3.5.0.dist-info/entry_points.txt
toefl_ibt_gaofen_zuowen-2024.3.5.0.dist-info/top_level.txt
toefl_ibt_gaofen_zuowen-2024.3.5.0.dist-info/RECORD
